setup_log/__init__.py
setup_log-0.0.2.dist-info/LICENSE
setup_log-0.0.2.dist-info/METADATA
setup_log-0.0.2.dist-info/WHEEL
setup_log-0.0.2.dist-info/top_level.txt
setup_log-0.0.2.dist-info/RECORD
